{"data":{"markdownRemark":{"html":"<p>Au petit matin, j'ai continué à étudier le livre \"MS_DOS6.0\" et à saisir de nouvelles fonctionnalités. L'utilisation d'un ordinateur a changé ma façon d'écrire des articles et a également changé ma façon de penser. L'idée principale est que le concept est différent: lorsque vous écrivez avec un stylo, les traits sont dessinés.Avec la méthode de saisie du pinyin de l'ordinateur, le premier est le son. Je ne sais pas quel genre de changements vont arriver aux personnes qui entrent par d'autres moyens. À l’avenir, il y aura différentes classes dans la société, divisées par différentes manières de penser créées par les ordinateurs.</p>","id":"/home/swain/workspace/political-life/src/pages/fr/0062.md absPath of file >>> MarkdownRemark","fileAbsolutePath":"/home/swain/workspace/political-life/src/pages/fr/0062.md","frontmatter":{"title":"\"18 mars vendredi\""}}},"pageContext":{"id":"/home/swain/workspace/political-life/src/pages/fr/0062.md absPath of file >>> MarkdownRemark"}}