{"data":{"markdownRemark":{"html":"<p>Viện Nghiên cứu Phát triển đã gặp gỡ để thảo luận về vấn đề viết \"Báo cáo Phát triển Trung Quốc 94\". Một số người đã vạch ra kế hoạch viết và đề xuất trao nó cho nhà xuất bản vào ngày 5 tháng 1 năm tới. Tôi hy vọng rằng tôi có thể đạt hiệu quả như năm ngoái.Trong hầu hết các trường hợp, nghiên cứu học thuật không thể hiệu quả.Tôi muốn nói về nó, nhưng đôi khi tôi phải có hiệu quả. Không có bản phát hành nhanh chóng mà không có sản phẩm dài và không có điểm nào trong việc không có sản phẩm dài hạn.</p>","id":"/home/swain/workspace/political-life/src/pages/vi/0154.md absPath of file >>> MarkdownRemark","fileAbsolutePath":"/home/swain/workspace/political-life/src/pages/vi/0154.md","frontmatter":{"title":"Thứ Sáu, ngày 7 tháng 10"}}},"pageContext":{"id":"/home/swain/workspace/political-life/src/pages/vi/0154.md absPath of file >>> MarkdownRemark"}}