{"data":{"markdownRemark":{"html":"<p>早朝に、私はTiger Booksの \"苦味\"を見ました。布虎シリーズは、外国で人気のある、またはベストセラーの小説に基づいて書かれた中国の登録商標の最初のセットであると言われています。 「苦い」とは、中国の医者が中国に帰ってきて誘拐されたことを意味し、冷たい顔をした殺人犯として訓練され、北京事務所に行き、中国の女の子と関係を築いた。それはよく作られた物語ですが、それは架空の物語です。それは人々に架空の痕跡があまりにも明白であると感じさせますが、そのような小説もそのようなスタイルです。主な「MSG」は、複数の女性と彼の関係です。</p>\n<p>「ベッド上での行動」はあまりにも多いようです。しかし、それは \"放棄された首都\"より少し少ないので、著者がいくつの単語を削除する必要はありません。これはベストセラーの本の第一歩であり、ある種の芸術的な領域を書いていないし、その物語の完全性と信頼性もあまり高くない。</p>\n<p>国際関係と国際政治における大学院の専門家の方向性について議論するためには、最先端の科学を目指し、自分の分野を更新し、より重要なことに、知識構造を更新しなければなりません。知識の更新がなければ、単一の更新方向の名前が機能しないことがあります。</p>","id":"/home/swain/workspace/political-life/src/pages/ja/0020.md absPath of file >>> MarkdownRemark","fileAbsolutePath":"/home/swain/workspace/political-life/src/pages/ja/0020.md","frontmatter":{"title":"1月28日 金曜日"}}},"pageContext":{"id":"/home/swain/workspace/political-life/src/pages/ja/0020.md absPath of file >>> MarkdownRemark"}}